{
    "homepage": "https://windows.php.net/downloads/releases/",
    "version": "8.0.17",
    "license": {
        "identifier": "PHP-3.01",
        "url": "https://secure.php.net/license/"
    },
    "architecture": {
        "64bit": {
            "url": "https://windows.php.net/downloads/releases/php-8.0.17-nts-Win32-vs16-x64.zip",
            "hash": "23f8fe47c869c99dac5624375a48f94c3915f6987c44a943f712f3b03e46a612"
        },
        "32bit": {
            "url": "https://windows.php.net/downloads/releases/php-8.0.17-nts-Win32-vs16-x86.zip",
            "hash": "a81ca7520e19e6bbcfd82e89d32b134fe7eb02a308c6d4eabf260110d9a34fcb"
        }
    },
    "bin": [
        "php.exe",
        "php-cgi.exe"
    ],
    "persist": "conf.d",
    "env_set": {
        "PHP_INI_SCAN_DIR": "$persist_dir;$dir\\conf.d;"
    },
    "post_install": "if($bucket) { . \"$(Find-BucketDirectory $bucket\\bin\\postinstall.ps1)\" -dir \"$dir\" }",
    "checkver": {
        "url": "https://windows.php.net/download/",
        "re": "<h3 id=\"php-8.0\".*?>.*?\\(([\\d.-]+)\\)</h3>"
    },
    "autoupdate": {
        "architecture": {
            "64bit": {
                "url": "https://windows.php.net/downloads/releases/php-$version-nts-Win32-vs16-x64.zip"
            },
            "32bit": {
                "url": "https://windows.php.net/downloads/releases/php-$version-nts-Win32-vs16-x86.zip"
            }
        },
        "hash": {
            "url": "$baseurl/sha256sum.txt"
        }
    },
    "suggest": {
        "vcredist": "extras/vcredist2019"
    }
}
